codenerix_cms/__init__.py
codenerix_cms/admin.py
codenerix_cms/apps.py
codenerix_cms/forms.py
codenerix_cms/models.py
codenerix_cms/templatetags_tags.py
codenerix_cms/urls.py
codenerix_cms/views.py
codenerix_cms/locale/en/LC_MESSAGES/django.po
codenerix_cms/locale/es/LC_MESSAGES/django.mo
codenerix_cms/locale/es/LC_MESSAGES/django.po
codenerix_cms/migrations/0001_initial.py
codenerix_cms/migrations/0002_auto_20170327_1021.py
codenerix_cms/migrations/0003_auto_20170418_1515.py
codenerix_cms/migrations/0004_auto_20170428_0850.py
codenerix_cms/migrations/0005_auto_20170517_1046.py
codenerix_cms/migrations/0006_auto_20171108_1628.py
codenerix_cms/migrations/0007_auto_20171115_1546.py
codenerix_cms/migrations/0008_auto_20171123_1019.py
codenerix_cms/migrations/__init__.py
codenerix_cms/migrations/__pycache__/0001_initial.cpython-35.pyc
codenerix_cms/migrations/__pycache__/0001_initial.cpython-39.pyc
codenerix_cms/migrations/__pycache__/0002_auto_20170327_1021.cpython-35.pyc
codenerix_cms/migrations/__pycache__/0002_auto_20170327_1021.cpython-39.pyc
codenerix_cms/migrations/__pycache__/0003_auto_20170418_1515.cpython-35.pyc
codenerix_cms/migrations/__pycache__/0003_auto_20170418_1515.cpython-39.pyc
codenerix_cms/migrations/__pycache__/0004_auto_20170428_0850.cpython-35.pyc
codenerix_cms/migrations/__pycache__/0004_auto_20170428_0850.cpython-39.pyc
codenerix_cms/migrations/__pycache__/0005_auto_20170517_1046.cpython-35.pyc
codenerix_cms/migrations/__pycache__/0005_auto_20170517_1046.cpython-39.pyc
codenerix_cms/migrations/__pycache__/0006_auto_20171108_1628.cpython-35.pyc
codenerix_cms/migrations/__pycache__/0006_auto_20171108_1628.cpython-39.pyc
codenerix_cms/migrations/__pycache__/0007_auto_20171115_1546.cpython-35.pyc
codenerix_cms/migrations/__pycache__/0007_auto_20171115_1546.cpython-39.pyc
codenerix_cms/migrations/__pycache__/0008_auto_20171123_1019.cpython-35.pyc
codenerix_cms/migrations/__pycache__/0008_auto_20171123_1019.cpython-39.pyc
django_codenerix_cms-4.0.1.dist-info/LICENSE
django_codenerix_cms-4.0.1.dist-info/METADATA
django_codenerix_cms-4.0.1.dist-info/WHEEL
django_codenerix_cms-4.0.1.dist-info/top_level.txt
django_codenerix_cms-4.0.1.dist-info/RECORD
